webuiapi/__init__.py
webuiapi/webuiapi.py
webuiapi-0.9.17.dist-info/LICENSE
webuiapi-0.9.17.dist-info/METADATA
webuiapi-0.9.17.dist-info/WHEEL
webuiapi-0.9.17.dist-info/top_level.txt
webuiapi-0.9.17.dist-info/RECORD
