Metadata-Version: 2.1
Name: webuiapi
Version: 0.9.17
Summary: Python API client for AUTOMATIC1111/stable-diffusion-webui
Home-page: https://github.com/mix1009/sdwebuiapi
Author: ChunKoo Park
Author-email: mix100f9@gmail.com
License: MIT
Keywords: stable-diffuion-webui,AUTOMATIC1111,stable-diffusion,api
Requires-Python: >=3.7, <4
License-File: LICENSE
